flask_mulang/__init__.py
flask_mulang/flask_multilananger.py
flask_mulang/generator.py
flask_mulang-1.1.0.dist-info/METADATA
flask_mulang-1.1.0.dist-info/WHEEL
flask_mulang-1.1.0.dist-info/top_level.txt
flask_mulang-1.1.0.dist-info/RECORD
