Metadata-Version: 2.1
Name: flask-mulang
Version: 1.1.0
Summary: Flask Extension for multi language support.
Author: Mohamed El-Hasnaouy
Author-email: <elhasnaouymed@proton.me>
Keywords: python,flask,language,babel,full stack,development
Classifier: Development Status :: 1 - Planning
Classifier: Intended Audience :: Developers
Classifier: Programming Language :: Python :: 3
Classifier: Operating System :: Unix
Classifier: Operating System :: MacOS :: MacOS X
Classifier: Operating System :: Microsoft :: Windows
Requires-Dist: flask
Requires-Dist: markdown
Requires-Dist: markupsafe
